PCMF/__init__.py
PCMF/Positive_CMF.py
pcmf-0.1.5.dist-info/LICENSE
pcmf-0.1.5.dist-info/WHEEL
pcmf-0.1.5.dist-info/METADATA
pcmf-0.1.5.dist-info/RECORD
