Metadata-Version: 2.1
Name: pcmf
Version: 0.1.5
Summary: PCMF is a Python package of Positive Collective Matrix Factorization(PCMF). PCMF is a model that combines the interpretability of NMF and the extensibility of CMF.
Home-page: https://github.com/N-YS-KK
License: MIT
Author: Y. Sumiya
Author-email: y.sumiya.1031@gmail.com
Requires-Python: >=3.6,<3.9
Classifier: Development Status :: 4 - Beta
Classifier: Intended Audience :: Science/Research
Classifier: License :: OSI Approved :: MIT License
Classifier: Programming Language :: Python :: 3
Classifier: Programming Language :: Python :: 3.6
Classifier: Programming Language :: Python :: 3.7
Classifier: Programming Language :: Python :: 3.8
Classifier: Topic :: Scientific/Engineering :: Artificial Intelligence
Requires-Dist: tensorflow (>=2.5.0,<3.0.0)
Project-URL: Repository, https://github.com/N-YS-KK/PCMF
